plip/__init__.py
plip/plipcmd.py
plip/basic/__init__.py
plip/basic/config.py
plip/basic/logger.py
plip/basic/parallel.py
plip/basic/remote.py
plip/basic/supplemental.py
plip/exchange/__init__.py
plip/exchange/json.py
plip/exchange/report.py
plip/exchange/webservices.py
plip/exchange/xml.py
plip/structure/__init__.py
plip/structure/detection.py
plip/structure/preparation.py
plip/test/__init__.py
plip/test/test_basic_functions.py
plip/test/test_command_line.py
plip/test/test_hydrogen_bonds.py
plip/test/test_intra.py
plip/test/test_literature_validated.py
plip/test/test_metal_coordination.py
plip/test/test_pi_stacking.py
plip/test/test_remote_services.py
plip/test/test_salt_bridges.py
plip/test/test_structure_processing.py
plip/test/test_visualization.py
plip/test/test_water_bridges.py
plip/test/test_xml_parser.py
plip/test/test_xml_writer.py
plip/visualization/__init__.py
plip/visualization/chimera.py
plip/visualization/pymol.py
plip/visualization/visualize.py
plip-2.3.1.data/scripts/plipcmd.py
plip-2.3.1.dist-info/LICENSE.txt
plip-2.3.1.dist-info/METADATA
plip-2.3.1.dist-info/WHEEL
plip-2.3.1.dist-info/entry_points.txt
plip-2.3.1.dist-info/top_level.txt
plip-2.3.1.dist-info/RECORD
